{
  "updatedAt": "2026-05-31T18:53:20+03:00",
  "timezone": "Asia/Jerusalem",
  "targetDate": "2026-06-01",
  "upcoming": {
    "total": 1,
    "message": null,
    "items": [
      {
        "date": "2026-05-31",
        "startTime": "22:00",
        "endTime": "23:00",
        "description": "מגרשים 1+2+4",
        "court": "מגרש 1",
        "location": "מגרשים 1+2+4"
      }
    ]
  },
  "configuredRequests": [
    {
      "id": "daily-20",
      "kind": "recurring",
      "targetDate": "2026-06-01",
      "targetDescription": "recurring",
      "startTime": "22:00",
      "courts": [
        "2",
        "1",
        "3"
      ]
    }
  ],
  "requests": [
    {
      "id": "daily-20",
      "kind": "recurring",
      "targetDate": "2026-06-01",
      "targetDescription": "recurring",
      "startTime": "22:00",
      "courts": [
        "2",
        "1",
        "3"
      ],
      "available": [
        "מגרש 4@classId:396",
        "מגרש 1@classId:435",
        "מגרש 2@classId:435",
        "מגרש 4@classId:435"
      ],
      "status": "available",
      "actionText": "הרשמה",
      "selectedCourt": "מגרש 2",
      "slot": "22:00-23:00"
    }
  ],
  "workflowRuns": {
    "booking": [
      {
        "updatedAt": "2026-05-31T15:04:55Z",
        "url": "https://github.com/sagi519/sportan-booker/actions/runs/26716134596",
        "createdAt": "2026-05-31T15:04:40Z",
        "event": "schedule",
        "number": 1,
        "headBranch": "main",
        "workflowName": "Sportan booking",
        "conclusion": "success",
        "databaseId": 26716134596,
        "status": "completed"
      }
    ]
  },
  "run": {
    "repository": "sagi519/sportan-booker",
    "runId": "26717248536",
    "runAttempt": "1",
    "workflow": "Sportan status",
    "url": "https://github.com/sagi519/sportan-booker/actions/runs/26717248536"
  }
}